README.md
setup.py
ProyectoP2/ProyectoJ.py
ProyectoP2/__init__.py
ProyectoP2.egg-info/PKG-INFO
ProyectoP2.egg-info/SOURCES.txt
ProyectoP2.egg-info/dependency_links.txt
ProyectoP2.egg-info/top_level.txt