Metadata-Version: 2.1
Name: ProyectoP2
Version: 0.4
Summary: Esta es la descripcion de mi paquete
Author: Juan Quezada
Author-email: 
License: MIT
Keywords: testing,logging,example
